knatch/__init__.py
knatch/quarto.py
knatch/utils.py
knatch-1.1.0.dist-info/LICENSE
knatch-1.1.0.dist-info/METADATA
knatch-1.1.0.dist-info/WHEEL
knatch-1.1.0.dist-info/entry_points.txt
knatch-1.1.0.dist-info/RECORD
